desmo_api/__init__.py
desmo_api/__main__.py
desmo_api/actions.py
desmo_api/api.py
desmo_api/db.py
desmo_api/fsm.py
desmo_api/hcloud_dns.py
desmo_api/log.py
desmo_api/models.py
desmo_api/prison_guard.py
desmo_api-0.5.0.dist-info/LICENSE
desmo_api-0.5.0.dist-info/METADATA
desmo_api-0.5.0.dist-info/WHEEL
desmo_api-0.5.0.dist-info/RECORD
