Metadata-Version: 2.1
Name: desmo-api
Version: 0.5.0
Summary: 
Author: Panu Oksiala
Author-email: panu@oksiala.fi
Requires-Python: >=3.9.18,<3.13
Classifier: Programming Language :: Python :: 3
Classifier: Programming Language :: Python :: 3.10
Classifier: Programming Language :: Python :: 3.11
Classifier: Programming Language :: Python :: 3.12
Requires-Dist: aiodns (>=3.1.1,<4.0.0)
Requires-Dist: aiohttp[speedups] (>=3.9.0,<4.0.0)
Requires-Dist: ansible (>=8.0.0,<9.0.0)
Requires-Dist: ansible-runner (>=2.3.4,<3.0.0)
Requires-Dist: asyncpg (>=0.29.0,<0.30.0)
Requires-Dist: fastapi (>=0.104.1,<0.105.0)
Requires-Dist: python-multipart (>=0.0.6,<0.0.7)
Requires-Dist: python-statemachine (>=2.1.2,<3.0.0)
